{"cheng2020_anchor": {"1": [{"class_id": 60, "name": "diningtable", "relative_coordinates": {"center_x": 0.510382, "center_y": 0.498274, "width": 1.009613, "height": 0.766721}, "confidence": 0.880493}, {"class_id": 55, "name": "cake", "relative_coordinates": {"center_x": 0.103265, "center_y": 0.466863, "width": 0.20824, "height": 0.375337}, "confidence": 0.582653}, {"class_id": 44, "name": "spoon", "relative_coordinates": {"center_x": 0.453205, "center_y": 0.537163, "width": 0.094897, "height": 0.187304}, "confidence": 0.784939}, {"class_id": 41, "name": "cup", "relative_coordinates": {"center_x": 0.618987, "center_y": 0.440021, "width": 0.355196, "height": 0.36735}, "confidence": 0.991709}, {"class_id": 41, "name": "cup", "relative_coordinates": {"center_x": 0.751972, "center_y": 0.215252, "width": 0.2161, "height": 0.300753}, "confidence": 0.663904}, {"class_id": 41, "name": "cup", "relative_coordinates": {"center_x": 0.757326, "center_y": 0.150611, "width": 0.202497, "height": 0.172347}, "confidence": 0.301471}], "2": [{"class_id": 60, "name": "diningtable", "relative_coordinates": {"center_x": 0.509273, "center_y": 0.494621, "width": 1.085302, "height": 0.776964}, "confidence": 0.933714}, {"class_id": 55, "name": "cake", "relative_coordinates": {"center_x": 0.102896, "center_y": 0.465518, "width": 0.204907, "height": 0.367262}, "confidence": 0.37065}, {"class_id": 45, "name": "bowl", "relative_coordinates": {"center_x": 0.219982, "center_y": 0.087484, "width": 0.295691, "height": 0.184157}, "confidence": 0.429735}, {"class_id": 44, "name": "spoon", "relative_coordinates": {"center_x": 0.453649, "center_y": 0.516462, "width": 0.093384, "height": 0.223187}, "confidence": 0.870984}, {"class_id": 41, "name": "cup", "relative_coordinates": {"center_x": 0.625451, "center_y": 0.439805, "width": 0.341113, "height": 0.364088}, "confidence": 0.989095}, {"class_id": 41, "name": "cup", "relative_coordinates": {"center_x": 0.758447, "center_y": 0.152526, "width": 0.208607, "height": 0.175553}, "confidence": 0.739149}], "3": [{"class_id": 60, "name": "diningtable", "relative_coordinates": {"center_x": 0.5081, "center_y": 0.495644, "width": 1.10859, "height": 0.77321}, "confidence": 0.938517}, {"class_id": 44, "name": "spoon", "relative_coordinates": {"center_x": 0.453577, "center_y": 0.514072, "width": 0.093755, "height": 0.230479}, "confidence": 0.881475}, {"class_id": 41, "name": "cup", "relative_coordinates": {"center_x": 0.626262, "center_y": 0.438986, "width": 0.336916, "height": 0.370078}, "confidence": 0.988141}, {"class_id": 41, "name": "cup", "relative_coordinates": {"center_x": 0.752886, "center_y": 0.204004, "width": 0.2167, "height": 0.294842}, "confidence": 0.973759}], "4": [{"class_id": 60, "name": "diningtable", "relative_coordinates": {"center_x": 0.506617, "center_y": 0.490956, "width": 1.112776, "height": 0.79331}, "confidence": 0.93805}, {"class_id": 45, "name": "bowl", "relative_coordinates": {"center_x": 0.2182, "center_y": 0.088515, "width": 0.296251, "height": 0.182955}, "confidence": 0.305442}, {"class_id": 44, "name": "spoon", "relative_coordinates": {"center_x": 0.454457, "center_y": 0.505409, "width": 0.080703, "height": 0.27164}, "confidence": 0.790991}, {"class_id": 41, "name": "cup", "relative_coordinates": {"center_x": 0.626558, "center_y": 0.439347, "width": 0.342257, "height": 0.362344}, "confidence": 0.991167}, {"class_id": 41, "name": "cup", "relative_coordinates": {"center_x": 0.752629, "center_y": 0.205558, "width": 0.220763, "height": 0.298604}, "confidence": 0.983116}], "5": [{"class_id": 60, "name": "diningtable", "relative_coordinates": {"center_x": 0.506789, "center_y": 0.490901, "width": 1.119936, "height": 0.811868}, "confidence": 0.964338}, {"class_id": 44, "name": "spoon", "relative_coordinates": {"center_x": 0.455036, "center_y": 0.50346, "width": 0.079777, "height": 0.278166}, "confidence": 0.895188}, {"class_id": 41, "name": "cup", "relative_coordinates": {"center_x": 0.622483, "center_y": 0.437183, "width": 0.336167, "height": 0.363709}, "confidence": 0.9918}, {"class_id": 41, "name": "cup", "relative_coordinates": {"center_x": 0.752239, "center_y": 0.205712, "width": 0.221369, "height": 0.297782}, "confidence": 0.991353}], "6": [{"class_id": 60, "name": "diningtable", "relative_coordinates": {"center_x": 0.506287, "center_y": 0.49012, "width": 1.151027, "height": 0.803916}, "confidence": 0.943473}, {"class_id": 45, "name": "bowl", "relative_coordinates": {"center_x": 0.216561, "center_y": 0.089494, "width": 0.29814, "height": 0.18424}, "confidence": 0.462224}, {"class_id": 44, "name": "spoon", "relative_coordinates": {"center_x": 0.455826, "center_y": 0.501065, "width": 0.080748, "height": 0.293409}, "confidence": 0.84909}, {"class_id": 41, "name": "cup", "relative_coordinates": {"center_x": 0.634855, "center_y": 0.44076, "width": 0.342953, "height": 0.360068}, "confidence": 0.990237}, {"class_id": 41, "name": "cup", "relative_coordinates": {"center_x": 0.752201, "center_y": 0.206234, "width": 0.22293, "height": 0.294933}, "confidence": 0.988426}], "curves": [[0.252, 0.358, 0.49, 0.744, 1.024, 1.343], [0.8820286562997963, 0.8495630597464972, 0.9460189196811875, 0.9081001728351126, 0.9022324525697247, 0.9055097236515233]], "integrate": 0.9051671319946994}, "webp": {"1": [{"class_id": 60, "name": "diningtable", "relative_coordinates": {"center_x": 0.508489, "center_y": 0.505028, "width": 0.928113, "height": 0.821805}, "confidence": 0.497149}, {"class_id": 55, "name": "cake", "relative_coordinates": {"center_x": 0.041547, "center_y": 0.504878, "width": 0.081444, "height": 0.358493}, "confidence": 0.286265}, {"class_id": 45, "name": "bowl", "relative_coordinates": {"center_x": 0.220936, "center_y": 0.089668, "width": 0.301581, "height": 0.1848}, "confidence": 0.780011}, {"class_id": 41, "name": "cup", "relative_coordinates": {"center_x": 0.616287, "center_y": 0.439781, "width": 0.352262, "height": 0.378852}, "confidence": 0.581996}], "2": [{"class_id": 60, "name": "diningtable", "relative_coordinates": {"center_x": 0.508489, "center_y": 0.505028, "width": 0.928113, "height": 0.821805}, "confidence": 0.497149}, {"class_id": 55, "name": "cake", "relative_coordinates": {"center_x": 0.041547, "center_y": 0.504878, "width": 0.081444, "height": 0.358493}, "confidence": 0.286265}, {"class_id": 45, "name": "bowl", "relative_coordinates": {"center_x": 0.220936, "center_y": 0.089668, "width": 0.301581, "height": 0.1848}, "confidence": 0.780011}, {"class_id": 41, "name": "cup", "relative_coordinates": {"center_x": 0.616287, "center_y": 0.439781, "width": 0.352262, "height": 0.378852}, "confidence": 0.581996}], "3": [{"class_id": 60, "name": "diningtable", "relative_coordinates": {"center_x": 0.511861, "center_y": 0.501302, "width": 1.012283, "height": 0.791123}, "confidence": 0.791945}, {"class_id": 55, "name": "cake", "relative_coordinates": {"center_x": 0.101901, "center_y": 0.480065, "width": 0.205307, "height": 0.388015}, "confidence": 0.381413}, {"class_id": 45, "name": "bowl", "relative_coordinates": {"center_x": 0.217201, "center_y": 0.090238, "width": 0.309185, "height": 0.18612}, "confidence": 0.650177}, {"class_id": 44, "name": "spoon", "relative_coordinates": {"center_x": 0.452685, "center_y": 0.502748, "width": 0.088045, "height": 0.277125}, "confidence": 0.446388}, {"class_id": 41, "name": "cup", "relative_coordinates": {"center_x": 0.621379, "center_y": 0.440028, "width": 0.350816, "height": 0.368244}, "confidence": 0.992559}, {"class_id": 41, "name": "cup", "relative_coordinates": {"center_x": 0.753092, "center_y": 0.18255, "width": 0.21007, "height": 0.248521}, "confidence": 0.78123}], "4": [{"class_id": 60, "name": "diningtable", "relative_coordinates": {"center_x": 0.511405, "center_y": 0.498182, "width": 1.056824, "height": 0.764367}, "confidence": 0.916237}, {"class_id": 44, "name": "spoon", "relative_coordinates": {"center_x": 0.452941, "center_y": 0.507152, "width": 0.080799, "height": 0.269989}, "confidence": 0.814383}, {"class_id": 41, "name": "cup", "relative_coordinates": {"center_x": 0.623619, "center_y": 0.438882, "width": 0.346757, "height": 0.359748}, "confidence": 0.990114}, {"class_id": 41, "name": "cup", "relative_coordinates": {"center_x": 0.751057, "center_y": 0.214007, "width": 0.211239, "height": 0.293513}, "confidence": 0.893962}], "5": [{"class_id": 60, "name": "diningtable", "relative_coordinates": {"center_x": 0.50956, "center_y": 0.496987, "width": 1.088064, "height": 0.784041}, "confidence": 0.938515}, {"class_id": 45, "name": "bowl", "relative_coordinates": {"center_x": 0.22351, "center_y": 0.08815, "width": 0.279994, "height": 0.185025}, "confidence": 0.295763}, {"class_id": 44, "name": "spoon", "relative_coordinates": {"center_x": 0.452852, "center_y": 0.517034, "width": 0.093931, "height": 0.217887}, "confidence": 0.860994}, {"class_id": 41, "name": "cup", "relative_coordinates": {"center_x": 0.623476, "center_y": 0.438752, "width": 0.344007, "height": 0.359668}, "confidence": 0.991746}, {"class_id": 41, "name": "cup", "relative_coordinates": {"center_x": 0.751584, "center_y": 0.21343, "width": 0.218277, "height": 0.300936}, "confidence": 0.977896}], "6": [{"class_id": 60, "name": "diningtable", "relative_coordinates": {"center_x": 0.509706, "center_y": 0.495696, "width": 1.122473, "height": 0.797641}, "confidence": 0.951077}, {"class_id": 45, "name": "bowl", "relative_coordinates": {"center_x": 0.216755, "center_y": 0.090235, "width": 0.295236, "height": 0.186247}, "confidence": 0.615632}, {"class_id": 44, "name": "spoon", "relative_coordinates": {"center_x": 0.452923, "center_y": 0.51888, "width": 0.092867, "height": 0.210838}, "confidence": 0.888846}, {"class_id": 41, "name": "cup", "relative_coordinates": {"center_x": 0.62437, "center_y": 0.438605, "width": 0.341225, "height": 0.361147}, "confidence": 0.992096}, {"class_id": 41, "name": "cup", "relative_coordinates": {"center_x": 0.752632, "center_y": 0.205305, "width": 0.222187, "height": 0.296451}, "confidence": 0.972308}], "curves": [[0.23557291666666666, 0.23557291666666666, 0.48583333333333334, 0.7234375, 1.00234375, 1.3413020833333333], [0.43755458242271983, 0.43755458242271983, 0.8531739977878219, 0.8800162079382027, 0.9409076022692788, 0.9504958454037244]], "integrate": 0.8518385583502297}}