{"cheng2020_anchor": {"1": [{"class_id": 8, "name": "boat", "relative_coordinates": {"center_x": 0.507699, "center_y": 0.656229, "width": 0.759676, "height": 0.125628}, "confidence": 0.384491}], "2": [{"class_id": 8, "name": "boat", "relative_coordinates": {"center_x": 0.512465, "center_y": 0.658476, "width": 0.773039, "height": 0.127386}, "confidence": 0.55746}, {"class_id": 8, "name": "boat", "relative_coordinates": {"center_x": 0.724137, "center_y": 0.571131, "width": 0.218608, "height": 0.042151}, "confidence": 0.271247}], "3": [{"class_id": 8, "name": "boat", "relative_coordinates": {"center_x": 0.50945, "center_y": 0.654061, "width": 0.764061, "height": 0.105667}, "confidence": 0.737575}, {"class_id": 8, "name": "boat", "relative_coordinates": {"center_x": 0.655819, "center_y": 0.608347, "width": 0.396301, "height": 0.056166}, "confidence": 0.353618}, {"class_id": 8, "name": "boat", "relative_coordinates": {"center_x": 0.709622, "center_y": 0.596412, "width": 0.404455, "height": 0.05787}, "confidence": 0.313492}, {"class_id": 8, "name": "boat", "relative_coordinates": {"center_x": 0.724431, "center_y": 0.571748, "width": 0.219623, "height": 0.040225}, "confidence": 0.269593}, {"class_id": 8, "name": "boat", "relative_coordinates": {"center_x": 0.722896, "center_y": 0.585252, "width": 0.235927, "height": 0.034933}, "confidence": 0.25864}], "4": [{"class_id": 8, "name": "boat", "relative_coordinates": {"center_x": 0.510214, "center_y": 0.657504, "width": 0.75237, "height": 0.096295}, "confidence": 0.595112}, {"class_id": 8, "name": "boat", "relative_coordinates": {"center_x": 0.710606, "center_y": 0.597026, "width": 0.398952, "height": 0.055504}, "confidence": 0.391565}, {"class_id": 8, "name": "boat", "relative_coordinates": {"center_x": 0.752531, "center_y": 0.586269, "width": 0.278169, "height": 0.040753}, "confidence": 0.340804}, {"class_id": 8, "name": "boat", "relative_coordinates": {"center_x": 0.655296, "center_y": 0.609929, "width": 0.370965, "height": 0.054198}, "confidence": 0.321926}], "5": [{"class_id": 8, "name": "boat", "relative_coordinates": {"center_x": 0.509522, "center_y": 0.658146, "width": 0.752272, "height": 0.092054}, "confidence": 0.472968}, {"class_id": 8, "name": "boat", "relative_coordinates": {"center_x": 0.710887, "center_y": 0.595543, "width": 0.387665, "height": 0.056023}, "confidence": 0.41646}, {"class_id": 8, "name": "boat", "relative_coordinates": {"center_x": 0.724148, "center_y": 0.585784, "width": 0.237739, "height": 0.036398}, "confidence": 0.39803}, {"class_id": 8, "name": "boat", "relative_coordinates": {"center_x": 0.654495, "center_y": 0.609637, "width": 0.388011, "height": 0.054585}, "confidence": 0.350883}, {"class_id": 8, "name": "boat", "relative_coordinates": {"center_x": 0.513078, "center_y": 0.605034, "width": 0.813131, "height": 0.196005}, "confidence": 0.307634}], "6": [{"class_id": 8, "name": "boat", "relative_coordinates": {"center_x": 0.510078, "center_y": 0.658213, "width": 0.77247, "height": 0.091959}, "confidence": 0.524727}, {"class_id": 8, "name": "boat", "relative_coordinates": {"center_x": 0.709791, "center_y": 0.59654, "width": 0.413035, "height": 0.058085}, "confidence": 0.421292}, {"class_id": 8, "name": "boat", "relative_coordinates": {"center_x": 0.724251, "center_y": 0.584925, "width": 0.236583, "height": 0.037772}, "confidence": 0.314777}, {"class_id": 8, "name": "boat", "relative_coordinates": {"center_x": 0.656076, "center_y": 0.610388, "width": 0.380161, "height": 0.056718}, "confidence": 0.285355}, {"class_id": 8, "name": "boat", "relative_coordinates": {"center_x": 0.514222, "center_y": 0.608127, "width": 0.826681, "height": 0.191557}, "confidence": 0.253386}], "curves": [[0.089, 0.134, 0.205, 0.375, 0.551, 0.776], [0.0, 0.4194528875379939, 0.48261449533125833, 0.4451154052603328, 0.781265839697242, 0.8153130468055911]], "integrate": 0.5936751061129313}, "webp": {"1": [{"class_id": 8, "name": "boat", "relative_coordinates": {"center_x": 0.502473, "center_y": 0.648182, "width": 0.715885, "height": 0.114245}, "confidence": 0.441079}], "2": [{"class_id": 8, "name": "boat", "relative_coordinates": {"center_x": 0.504933, "center_y": 0.654265, "width": 0.711472, "height": 0.100009}, "confidence": 0.554708}, {"class_id": 8, "name": "boat", "relative_coordinates": {"center_x": 0.710704, "center_y": 0.601648, "width": 0.280792, "height": 0.057414}, "confidence": 0.301304}, {"class_id": 8, "name": "boat", "relative_coordinates": {"center_x": 0.932033, "center_y": 0.564109, "width": 0.088864, "height": 0.05749}, "confidence": 0.260162}], "3": [{"class_id": 8, "name": "boat", "relative_coordinates": {"center_x": 0.511162, "center_y": 0.651623, "width": 0.730207, "height": 0.100663}, "confidence": 0.431455}, {"class_id": 8, "name": "boat", "relative_coordinates": {"center_x": 0.537291, "center_y": 0.610416, "width": 0.811358, "height": 0.159757}, "confidence": 0.368178}, {"class_id": 8, "name": "boat", "relative_coordinates": {"center_x": 0.6596, "center_y": 0.611013, "width": 0.305117, "height": 0.056149}, "confidence": 0.272299}, {"class_id": 8, "name": "boat", "relative_coordinates": {"center_x": 0.713456, "center_y": 0.596185, "width": 0.310984, "height": 0.058021}, "confidence": 0.266132}], "4": [{"class_id": 8, "name": "boat", "relative_coordinates": {"center_x": 0.513295, "center_y": 0.650602, "width": 0.764818, "height": 0.105353}, "confidence": 0.678685}, {"class_id": 8, "name": "boat", "relative_coordinates": {"center_x": 0.655642, "center_y": 0.606956, "width": 0.349734, "height": 0.054371}, "confidence": 0.36449}, {"class_id": 8, "name": "boat", "relative_coordinates": {"center_x": 0.710412, "center_y": 0.596025, "width": 0.391744, "height": 0.060008}, "confidence": 0.333715}, {"class_id": 8, "name": "boat", "relative_coordinates": {"center_x": 0.72295, "center_y": 0.571941, "width": 0.224706, "height": 0.03613}, "confidence": 0.307809}], "5": [{"class_id": 8, "name": "boat", "relative_coordinates": {"center_x": 0.507249, "center_y": 0.6508, "width": 0.752113, "height": 0.100701}, "confidence": 0.648282}, {"class_id": 8, "name": "boat", "relative_coordinates": {"center_x": 0.709704, "center_y": 0.596494, "width": 0.347316, "height": 0.057349}, "confidence": 0.370693}, {"class_id": 8, "name": "boat", "relative_coordinates": {"center_x": 0.655587, "center_y": 0.610269, "width": 0.334647, "height": 0.054574}, "confidence": 0.368366}, {"class_id": 8, "name": "boat", "relative_coordinates": {"center_x": 0.723849, "center_y": 0.584932, "width": 0.235935, "height": 0.035361}, "confidence": 0.314901}], "6": [{"class_id": 8, "name": "boat", "relative_coordinates": {"center_x": 0.510323, "center_y": 0.65175, "width": 0.758269, "height": 0.103494}, "confidence": 0.649167}, {"class_id": 8, "name": "boat", "relative_coordinates": {"center_x": 0.711425, "center_y": 0.593839, "width": 0.359214, "height": 0.05805}, "confidence": 0.472516}, {"class_id": 8, "name": "boat", "relative_coordinates": {"center_x": 0.722125, "center_y": 0.585099, "width": 0.231282, "height": 0.037833}, "confidence": 0.427177}, {"class_id": 8, "name": "boat", "relative_coordinates": {"center_x": 0.656744, "center_y": 0.609814, "width": 0.353355, "height": 0.055018}, "confidence": 0.373412}], "curves": [[0.09248826291079812, 0.12564553990610328, 0.20099765258215962, 0.36396713615023474, 0.5415492957746478, 0.768368544600939], [0.4224551393368064, 0.4337090713902308, 0.44516013598139204, 0.4658653846153846, 0.4651994990159241, 0.9389167000327667]], "integrate": 0.5377455135545159}}