{"cheng2020_anchor": {"1": [{"class_id": 75, "name": "vase", "relative_coordinates": {"center_x": 0.928569, "center_y": 0.912717, "width": 0.143386, "height": 0.175428}, "confidence": 0.271078}], "2": [], "3": [], "4": [{"class_id": 77, "name": "teddy bear", "relative_coordinates": {"center_x": 0.512482, "center_y": 0.637642, "width": 0.219451, "height": 0.240821}, "confidence": 0.938381}, {"class_id": 77, "name": "teddy bear", "relative_coordinates": {"center_x": 0.365841, "center_y": 0.498584, "width": 0.167221, "height": 0.200032}, "confidence": 0.666903}, {"class_id": 77, "name": "teddy bear", "relative_coordinates": {"center_x": 0.609964, "center_y": 0.545402, "width": 0.109722, "height": 0.157033}, "confidence": 0.505915}, {"class_id": 77, "name": "teddy bear", "relative_coordinates": {"center_x": 0.723301, "center_y": 0.702094, "width": 0.236829, "height": 0.22633}, "confidence": 0.447305}, {"class_id": 59, "name": "bed", "relative_coordinates": {"center_x": 0.540894, "center_y": 0.716771, "width": 0.691059, "height": 0.527312}, "confidence": 0.459854}], "5": [{"class_id": 77, "name": "teddy bear", "relative_coordinates": {"center_x": 0.510455, "center_y": 0.637884, "width": 0.215878, "height": 0.24405}, "confidence": 0.939022}, {"class_id": 77, "name": "teddy bear", "relative_coordinates": {"center_x": 0.365631, "center_y": 0.497493, "width": 0.165278, "height": 0.19565}, "confidence": 0.910458}, {"class_id": 77, "name": "teddy bear", "relative_coordinates": {"center_x": 0.722367, "center_y": 0.697163, "width": 0.240029, "height": 0.235601}, "confidence": 0.677849}, {"class_id": 77, "name": "teddy bear", "relative_coordinates": {"center_x": 0.609953, "center_y": 0.549828, "width": 0.110683, "height": 0.167349}, "confidence": 0.643533}, {"class_id": 77, "name": "teddy bear", "relative_coordinates": {"center_x": 0.575366, "center_y": 0.442228, "width": 0.097129, "height": 0.132036}, "confidence": 0.303854}, {"class_id": 77, "name": "teddy bear", "relative_coordinates": {"center_x": 0.689919, "center_y": 0.556514, "width": 0.07146, "height": 0.087819}, "confidence": 0.271908}, {"class_id": 59, "name": "bed", "relative_coordinates": {"center_x": 0.517556, "center_y": 0.72033, "width": 0.695557, "height": 0.507751}, "confidence": 0.359046}], "6": [{"class_id": 77, "name": "teddy bear", "relative_coordinates": {"center_x": 0.365592, "center_y": 0.496989, "width": 0.170411, "height": 0.199037}, "confidence": 0.973586}, {"class_id": 77, "name": "teddy bear", "relative_coordinates": {"center_x": 0.513015, "center_y": 0.637103, "width": 0.225594, "height": 0.236886}, "confidence": 0.924768}, {"class_id": 77, "name": "teddy bear", "relative_coordinates": {"center_x": 0.724077, "center_y": 0.702631, "width": 0.234574, "height": 0.225548}, "confidence": 0.718944}, {"class_id": 77, "name": "teddy bear", "relative_coordinates": {"center_x": 0.608815, "center_y": 0.546353, "width": 0.113829, "height": 0.152677}, "confidence": 0.586978}, {"class_id": 77, "name": "teddy bear", "relative_coordinates": {"center_x": 0.574542, "center_y": 0.447817, "width": 0.093033, "height": 0.144926}, "confidence": 0.511861}, {"class_id": 77, "name": "teddy bear", "relative_coordinates": {"center_x": 0.559924, "center_y": 0.653919, "width": 0.133528, "height": 0.180124}, "confidence": 0.259417}, {"class_id": 59, "name": "bed", "relative_coordinates": {"center_x": 0.51702, "center_y": 0.723535, "width": 0.699502, "height": 0.51411}, "confidence": 0.614515}], "curves": [[0.24, 0.354, 0.489, 0.802, 1.072, 1.378], [0.0, 0.0, 0.0, 0.5837020382567004, 0.46395317673095055, 0.706497163334601]], "integrate": 0.3619171573291176}, "webp": {"1": [{"class_id": 75, "name": "vase", "relative_coordinates": {"center_x": 0.063281, "center_y": 0.667891, "width": 0.127087, "height": 0.26075}, "confidence": 0.405972}, {"class_id": 75, "name": "vase", "relative_coordinates": {"center_x": 0.900506, "center_y": 0.493021, "width": 0.203861, "height": 0.963985}, "confidence": 0.382277}], "2": [], "3": [], "4": [{"class_id": 77, "name": "teddy bear", "relative_coordinates": {"center_x": 0.723376, "center_y": 0.704391, "width": 0.199196, "height": 0.225943}, "confidence": 0.367583}, {"class_id": 77, "name": "teddy bear", "relative_coordinates": {"center_x": 0.512635, "center_y": 0.640196, "width": 0.219826, "height": 0.241428}, "confidence": 0.357755}, {"class_id": 75, "name": "vase", "relative_coordinates": {"center_x": 0.110538, "center_y": 0.647982, "width": 0.049962, "height": 0.231806}, "confidence": 0.47489}], "5": [{"class_id": 77, "name": "teddy bear", "relative_coordinates": {"center_x": 0.365064, "center_y": 0.499007, "width": 0.169521, "height": 0.203576}, "confidence": 0.908269}, {"class_id": 77, "name": "teddy bear", "relative_coordinates": {"center_x": 0.507586, "center_y": 0.636524, "width": 0.21461, "height": 0.234982}, "confidence": 0.790927}, {"class_id": 77, "name": "teddy bear", "relative_coordinates": {"center_x": 0.716036, "center_y": 0.704773, "width": 0.219899, "height": 0.219049}, "confidence": 0.777994}, {"class_id": 77, "name": "teddy bear", "relative_coordinates": {"center_x": 0.603619, "center_y": 0.543921, "width": 0.093266, "height": 0.153615}, "confidence": 0.504221}, {"class_id": 77, "name": "teddy bear", "relative_coordinates": {"center_x": 0.562296, "center_y": 0.653652, "width": 0.112967, "height": 0.168004}, "confidence": 0.323153}], "6": [{"class_id": 77, "name": "teddy bear", "relative_coordinates": {"center_x": 0.511041, "center_y": 0.628189, "width": 0.219183, "height": 0.240927}, "confidence": 0.950167}, {"class_id": 77, "name": "teddy bear", "relative_coordinates": {"center_x": 0.364922, "center_y": 0.498619, "width": 0.168843, "height": 0.204472}, "confidence": 0.905285}, {"class_id": 77, "name": "teddy bear", "relative_coordinates": {"center_x": 0.723475, "center_y": 0.70279, "width": 0.217188, "height": 0.223896}, "confidence": 0.805924}, {"class_id": 77, "name": "teddy bear", "relative_coordinates": {"center_x": 0.607364, "center_y": 0.551957, "width": 0.102229, "height": 0.170591}, "confidence": 0.622512}, {"class_id": 77, "name": "teddy bear", "relative_coordinates": {"center_x": 0.662609, "center_y": 0.596923, "width": 0.128557, "height": 0.197979}, "confidence": 0.323747}], "curves": [[0.200625, 0.32135416666666666, 0.465625, 0.8164583333333333, 1.0652083333333333, 1.3511458333333333], [0.0, 0.0, 0.0, 0.0, 0.44312874567477784, 0.45130658019629377]], "integrate": 0.1590500866540272}}