{"cheng2020_anchor": {"1": [{"class_id": 45, "name": "bowl", "relative_coordinates": {"center_x": 0.502762, "center_y": 0.706628, "width": 0.950952, "height": 0.584966}, "confidence": 0.972006}, {"class_id": 45, "name": "bowl", "relative_coordinates": {"center_x": 0.725521, "center_y": 0.250115, "width": 0.509785, "height": 0.522091}, "confidence": 0.825141}, {"class_id": 45, "name": "bowl", "relative_coordinates": {"center_x": 0.339716, "center_y": 0.447229, "width": 0.690249, "height": 0.843933}, "confidence": 0.343459}, {"class_id": 45, "name": "bowl", "relative_coordinates": {"center_x": 0.898827, "center_y": 0.623286, "width": 0.204596, "height": 0.429044}, "confidence": 0.259081}], "2": [{"class_id": 45, "name": "bowl", "relative_coordinates": {"center_x": 0.500123, "center_y": 0.706903, "width": 0.973123, "height": 0.596174}, "confidence": 0.966455}, {"class_id": 45, "name": "bowl", "relative_coordinates": {"center_x": 0.726729, "center_y": 0.250692, "width": 0.517127, "height": 0.510332}, "confidence": 0.937761}, {"class_id": 45, "name": "bowl", "relative_coordinates": {"center_x": 0.339702, "center_y": 0.448495, "width": 0.717669, "height": 0.865321}, "confidence": 0.36775}], "3": [{"class_id": 45, "name": "bowl", "relative_coordinates": {"center_x": 0.504132, "center_y": 0.706905, "width": 0.956173, "height": 0.584055}, "confidence": 0.972771}, {"class_id": 45, "name": "bowl", "relative_coordinates": {"center_x": 0.722169, "center_y": 0.251543, "width": 0.522007, "height": 0.509389}, "confidence": 0.932751}, {"class_id": 45, "name": "bowl", "relative_coordinates": {"center_x": 0.342541, "center_y": 0.499941, "width": 0.676686, "height": 0.908682}, "confidence": 0.578547}], "4": [{"class_id": 45, "name": "bowl", "relative_coordinates": {"center_x": 0.501205, "center_y": 0.709136, "width": 0.954975, "height": 0.590825}, "confidence": 0.96307}, {"class_id": 45, "name": "bowl", "relative_coordinates": {"center_x": 0.723091, "center_y": 0.250053, "width": 0.525047, "height": 0.509771}, "confidence": 0.9116}, {"class_id": 45, "name": "bowl", "relative_coordinates": {"center_x": 0.342839, "center_y": 0.500561, "width": 0.690804, "height": 0.91029}, "confidence": 0.631143}], "5": [{"class_id": 45, "name": "bowl", "relative_coordinates": {"center_x": 0.501745, "center_y": 0.708856, "width": 0.932423, "height": 0.58592}, "confidence": 0.965904}, {"class_id": 45, "name": "bowl", "relative_coordinates": {"center_x": 0.723971, "center_y": 0.249058, "width": 0.525765, "height": 0.510123}, "confidence": 0.934717}, {"class_id": 45, "name": "bowl", "relative_coordinates": {"center_x": 0.337956, "center_y": 0.451874, "width": 0.66795, "height": 0.876659}, "confidence": 0.774909}], "6": [{"class_id": 45, "name": "bowl", "relative_coordinates": {"center_x": 0.50093, "center_y": 0.707894, "width": 0.936755, "height": 0.591368}, "confidence": 0.956928}, {"class_id": 45, "name": "bowl", "relative_coordinates": {"center_x": 0.723405, "center_y": 0.249542, "width": 0.528292, "height": 0.510338}, "confidence": 0.945646}, {"class_id": 45, "name": "bowl", "relative_coordinates": {"center_x": 0.34145, "center_y": 0.502408, "width": 0.67466, "height": 0.931772}, "confidence": 0.752103}], "curves": [[0.177, 0.249, 0.34, 0.507, 0.675, 0.875], [0.6483266306172855, 0.6420738169506687, 0.9332734655134387, 0.9296272170392109, 0.9628381376409063, 0.9330803293908594]], "integrate": 0.8914668495043209}, "webp": {"1": [{"class_id": 45, "name": "bowl", "relative_coordinates": {"center_x": 0.502383, "center_y": 0.702778, "width": 0.945232, "height": 0.618865}, "confidence": 0.782106}], "2": [{"class_id": 45, "name": "bowl", "relative_coordinates": {"center_x": 0.502383, "center_y": 0.702778, "width": 0.945232, "height": 0.618865}, "confidence": 0.782106}], "3": [{"class_id": 45, "name": "bowl", "relative_coordinates": {"center_x": 0.499307, "center_y": 0.708673, "width": 0.945539, "height": 0.64101}, "confidence": 0.963104}, {"class_id": 45, "name": "bowl", "relative_coordinates": {"center_x": 0.711731, "center_y": 0.248431, "width": 0.543056, "height": 0.516874}, "confidence": 0.754206}, {"class_id": 45, "name": "bowl", "relative_coordinates": {"center_x": 0.337607, "center_y": 0.447472, "width": 0.667163, "height": 0.845912}, "confidence": 0.396076}], "4": [{"class_id": 50, "name": "broccoli", "relative_coordinates": {"center_x": 0.4975, "center_y": 0.749004, "width": 0.942739, "height": 0.506722}, "confidence": 0.268473}, {"class_id": 45, "name": "bowl", "relative_coordinates": {"center_x": 0.497072, "center_y": 0.708278, "width": 0.947649, "height": 0.627901}, "confidence": 0.939009}, {"class_id": 45, "name": "bowl", "relative_coordinates": {"center_x": 0.715399, "center_y": 0.248422, "width": 0.535878, "height": 0.520155}, "confidence": 0.831643}, {"class_id": 45, "name": "bowl", "relative_coordinates": {"center_x": 0.342167, "center_y": 0.499983, "width": 0.684047, "height": 0.916483}, "confidence": 0.388002}], "5": [{"class_id": 45, "name": "bowl", "relative_coordinates": {"center_x": 0.49729, "center_y": 0.709345, "width": 0.954309, "height": 0.618199}, "confidence": 0.923744}, {"class_id": 45, "name": "bowl", "relative_coordinates": {"center_x": 0.719839, "center_y": 0.249178, "width": 0.533434, "height": 0.525493}, "confidence": 0.904044}, {"class_id": 45, "name": "bowl", "relative_coordinates": {"center_x": 0.340266, "center_y": 0.45098, "width": 0.668582, "height": 0.86745}, "confidence": 0.581938}], "6": [{"class_id": 45, "name": "bowl", "relative_coordinates": {"center_x": 0.501852, "center_y": 0.70725, "width": 0.948781, "height": 0.614951}, "confidence": 0.951864}, {"class_id": 45, "name": "bowl", "relative_coordinates": {"center_x": 0.718204, "center_y": 0.249316, "width": 0.519418, "height": 0.520058}, "confidence": 0.900531}, {"class_id": 45, "name": "bowl", "relative_coordinates": {"center_x": 0.338358, "center_y": 0.450799, "width": 0.679354, "height": 0.876452}, "confidence": 0.585511}], "curves": [[0.17916666666666667, 0.17916666666666667, 0.33171875, 0.4948958333333333, 0.6674479166666667, 0.87109375], [0.3218226080565891, 0.3218226080565891, 0.623888026849497, 0.6365781054621488, 0.9734181749650217, 0.977475434687317]], "integrate": 0.7407203060959041}}